{
  "size": 20,
  "opt_val": -26.0,
  "method": "AWQV",
  "operations": [
    "Y0",
    "Y1",
    "Y2",
    "Y3",
    "Y4",
    "Y5",
    "Y6",
    "Y7",
    "Y8",
    "Y9",
    "Y10",
    "Y11",
    "Y12",
    "Y13",
    "Y14",
    "Y15",
    "Y16",
    "Y17",
    "Y18",
    "Y19",
    "Z0_Y17",
    "Z1_Y16",
    "Z2_Y15",
    "Z3_Y14",
    "Z4_Y13",
    "Z5_Y12",
    "Z6_Y11",
    "Z7_Y10",
    "Z8_Y9",
    "Z18_Y19",
    "Y0_Z17",
    "Y1_Z16",
    "Y2_Z15",
    "Y3_Z14",
    "Y4_Z13",
    "Y5_Z12",
    "Y6_Z11",
    "Y7_Z10",
    "Y8_Z9",
    "Y18_Z19",
    "Z18_Y16",
    "Z0_Y15",
    "Z1_Y14",
    "Z2_Y13",
    "Z3_Y12",
    "Z4_Y11",
    "Z5_Y10",
    "Z6_Y9",
    "Z7_Y8",
    "Z17_Y19",
    "Y18_Z16",
    "Y0_Z15",
    "Y1_Z14",
    "Y2_Z13",
    "Y3_Z12",
    "Y4_Z11",
    "Y5_Z10",
    "Y6_Z9",
    "Y7_Z8",
    "Y17_Z19",
    "Z17_Y15",
    "Z18_Y14",
    "Z0_Y13",
    "Z1_Y12",
    "Z2_Y11",
    "Z3_Y10",
    "Z4_Y9",
    "Z5_Y8",
    "Z6_Y7",
    "Z16_Y19",
    "Y17_Z15",
    "Y18_Z14",
    "Y0_Z13",
    "Y1_Z12",
    "Y2_Z11",
    "Y3_Z10",
    "Y4_Z9",
    "Y5_Z8",
    "Y6_Z7",
    "Y16_Z19",
    "Z16_Y14",
    "Z17_Y13",
    "Z18_Y12",
    "Z0_Y11",
    "Z1_Y10",
    "Z2_Y9",
    "Z3_Y8",
    "Z4_Y7",
    "Z5_Y6",
    "Z15_Y19",
    "Y16_Z14",
    "Y17_Z13",
    "Y18_Z12",
    "Y0_Z11",
    "Y1_Z10",
    "Y2_Z9",
    "Y3_Z8",
    "Y4_Z7",
    "Y5_Z6",
    "Y15_Z19",
    "Z15_Y13",
    "Z16_Y12",
    "Z17_Y11",
    "Z18_Y10",
    "Z0_Y9",
    "Z1_Y8",
    "Z2_Y7",
    "Z3_Y6",
    "Z4_Y5",
    "Z14_Y19",
    "Y15_Z13",
    "Y16_Z12",
    "Y17_Z11",
    "Y18_Z10",
    "Y0_Z9",
    "Y1_Z8",
    "Y2_Z7",
    "Y3_Z6",
    "Y4_Z5",
    "Y14_Z19",
    "Z14_Y12",
    "Z15_Y11",
    "Z16_Y10",
    "Z17_Y9",
    "Z18_Y8",
    "Z0_Y7",
    "Z1_Y6",
    "Z2_Y5",
    "Z3_Y4",
    "Z13_Y19",
    "Y14_Z12",
    "Y15_Z11",
    "Y16_Z10",
    "Y17_Z9",
    "Y18_Z8",
    "Y0_Z7",
    "Y1_Z6",
    "Y2_Z5",
    "Y3_Z4",
    "Y13_Z19",
    "Z13_Y11",
    "Z14_Y10",
    "Z15_Y9",
    "Z16_Y8",
    "Z17_Y7",
    "Z18_Y6",
    "Z0_Y5",
    "Z1_Y4",
    "Z2_Y3",
    "Z12_Y19",
    "Y13_Z11",
    "Y14_Z10",
    "Y15_Z9",
    "Y16_Z8",
    "Y17_Z7",
    "Y18_Z6",
    "Y0_Z5",
    "Y1_Z4",
    "Y2_Z3",
    "Y12_Z19",
    "Z12_Y10",
    "Z13_Y9",
    "Z14_Y8",
    "Z15_Y7",
    "Z16_Y6",
    "Z17_Y5",
    "Z18_Y4",
    "Z0_Y3",
    "Z1_Y2",
    "Z11_Y19",
    "Y12_Z10",
    "Y13_Z9",
    "Y14_Z8",
    "Y15_Z7",
    "Y16_Z6",
    "Y17_Z5",
    "Y18_Z4",
    "Y0_Z3",
    "Y1_Z2",
    "Y11_Z19",
    "Z11_Y9",
    "Z12_Y8",
    "Z13_Y7",
    "Z14_Y6",
    "Z15_Y5",
    "Z16_Y4",
    "Z17_Y3",
    "Z18_Y2",
    "Z0_Y1",
    "Z10_Y19",
    "Y11_Z9",
    "Y12_Z8",
    "Y13_Z7",
    "Y14_Z6",
    "Y15_Z5",
    "Y16_Z4",
    "Y17_Z3",
    "Y18_Z2",
    "Y0_Z1",
    "Y10_Z19",
    "Z10_Y8",
    "Z11_Y7",
    "Z12_Y6",
    "Z13_Y5",
    "Z14_Y4",
    "Z15_Y3",
    "Z16_Y2",
    "Z17_Y1",
    "Z18_Y0",
    "Z9_Y19",
    "Y10_Z8",
    "Y11_Z7",
    "Y12_Z6",
    "Y13_Z5",
    "Y14_Z4",
    "Y15_Z3",
    "Y16_Z2",
    "Y17_Z1",
    "Y18_Z0",
    "Y9_Z19",
    "Z9_Y7",
    "Z10_Y6",
    "Z11_Y5",
    "Z12_Y4",
    "Z13_Y3",
    "Z14_Y2",
    "Z15_Y1",
    "Z16_Y0",
    "Z17_Y18",
    "Z8_Y19",
    "Y9_Z7",
    "Y10_Z6",
    "Y11_Z5",
    "Y12_Z4",
    "Y13_Z3",
    "Y14_Z2",
    "Y15_Z1",
    "Y16_Z0",
    "Y17_Z18",
    "Y8_Z19",
    "Z8_Y6",
    "Z9_Y5",
    "Z10_Y4",
    "Z11_Y3",
    "Z12_Y2",
    "Z13_Y1",
    "Z14_Y0",
    "Z15_Y18",
    "Z16_Y17",
    "Z7_Y19",
    "Y8_Z6",
    "Y9_Z5",
    "Y10_Z4",
    "Y11_Z3",
    "Y12_Z2",
    "Y13_Z1",
    "Y14_Z0",
    "Y15_Z18",
    "Y16_Z17",
    "Y7_Z19",
    "Z7_Y5",
    "Z8_Y4",
    "Z9_Y3",
    "Z10_Y2",
    "Z11_Y1",
    "Z12_Y0",
    "Z13_Y18",
    "Z14_Y17",
    "Z15_Y16",
    "Z6_Y19",
    "Y7_Z5",
    "Y8_Z4",
    "Y9_Z3",
    "Y10_Z2",
    "Y11_Z1",
    "Y12_Z0",
    "Y13_Z18",
    "Y14_Z17",
    "Y15_Z16",
    "Y6_Z19",
    "Z6_Y4",
    "Z7_Y3",
    "Z8_Y2",
    "Z9_Y1",
    "Z10_Y0",
    "Z11_Y18",
    "Z12_Y17",
    "Z13_Y16",
    "Z14_Y15",
    "Z5_Y19",
    "Y6_Z4",
    "Y7_Z3",
    "Y8_Z2",
    "Y9_Z1",
    "Y10_Z0",
    "Y11_Z18",
    "Y12_Z17",
    "Y13_Z16",
    "Y14_Z15",
    "Y5_Z19",
    "Z5_Y3",
    "Z6_Y2",
    "Z7_Y1",
    "Z8_Y0",
    "Z9_Y18",
    "Z10_Y17",
    "Z11_Y16",
    "Z12_Y15",
    "Z13_Y14",
    "Z4_Y19",
    "Y5_Z3",
    "Y6_Z2",
    "Y7_Z1",
    "Y8_Z0",
    "Y9_Z18",
    "Y10_Z17",
    "Y11_Z16",
    "Y12_Z15",
    "Y13_Z14",
    "Y4_Z19",
    "Z4_Y2",
    "Z5_Y1",
    "Z6_Y0",
    "Z7_Y18",
    "Z8_Y17",
    "Z9_Y16",
    "Z10_Y15",
    "Z11_Y14",
    "Z12_Y13",
    "Z3_Y19",
    "Y4_Z2",
    "Y5_Z1",
    "Y6_Z0",
    "Y7_Z18",
    "Y8_Z17",
    "Y9_Z16",
    "Y10_Z15",
    "Y11_Z14",
    "Y12_Z13",
    "Y3_Z19",
    "Z3_Y1",
    "Z4_Y0",
    "Z5_Y18",
    "Z6_Y17",
    "Z7_Y16",
    "Z8_Y15",
    "Z9_Y14",
    "Z10_Y13",
    "Z11_Y12",
    "Z2_Y19",
    "Y3_Z1",
    "Y4_Z0",
    "Y5_Z18",
    "Y6_Z17",
    "Y7_Z16",
    "Y8_Z15",
    "Y9_Z14",
    "Y10_Z13",
    "Y11_Z12",
    "Y2_Z19",
    "Z2_Y0",
    "Z3_Y18",
    "Z4_Y17",
    "Z5_Y16",
    "Z6_Y15",
    "Z7_Y14",
    "Z8_Y13",
    "Z9_Y12",
    "Z10_Y11",
    "Z1_Y19",
    "Y2_Z0",
    "Y3_Z18",
    "Y4_Z17",
    "Y5_Z16",
    "Y6_Z15",
    "Y7_Z14",
    "Y8_Z13",
    "Y9_Z12",
    "Y10_Z11",
    "Y1_Z19",
    "Z1_Y18",
    "Z2_Y17",
    "Z3_Y16",
    "Z4_Y15",
    "Z5_Y14",
    "Z6_Y13",
    "Z7_Y12",
    "Z8_Y11",
    "Z9_Y10",
    "Z0_Y19",
    "Y1_Z18",
    "Y2_Z17",
    "Y3_Z16",
    "Y4_Z15",
    "Y5_Z14",
    "Y6_Z13",
    "Y7_Z12",
    "Y8_Z11",
    "Y9_Z10",
    "Y0_Z19"
  ],
  "dt": 0.05,
  "lr": 0.05,
  "lam": 1.0,
  "mu": 0.9,
  "fix_step": 0,
  "constant_c": true,
  "parameters": [
    -1.2597741260833573e-05,
    -1.1413784584135556e-08,
    -2.5537323381286114e-05,
    -2.542958839057974e-07,
    5.920746843912639e-06,
    -4.035725578432903e-05,
    3.169108367728768e-06,
    -0.00025147260748781264,
    9.83175368673983e-07,
    6.502466931124218e-06,
    0.0004075881151948124,
    -1.4588701560569461e-05,
    7.139705758163473e-06,
    1.847485691541806e-05,
    -1.3794384358334355e-05,
    4.341798194218427e-05,
    -1.0578422916296404e-05,
    1.821515616029501e-05,
    -5.222919753578026e-06,
    -6.948322152311448e-06,
    0.7386775016784668,
    -0.004027067217975855,
    0.18807758390903473,
    -0.05635528638958931,
    0.13687019050121307,
    -0.08490899205207825,
    -0.015408162958920002,
    0.5523572564125061,
    -0.09535704553127289,
    0.11344945430755615,
    -0.7051039338111877,
    0.0011581070721149445,
    -0.1992858648300171,
    0.060504499822854996,
    -0.13971109688282013,
    0.08856014162302017,
    0.0149887939915061,
    1.0041813850402832,
    0.09816727787256241,
    -0.11676958203315735,
    1.4085373878479004,
    -0.012764552608132362,
    0.07557861506938934,
    -0.22493214905261993,
    0.1151391789317131,
    0.3192524015903473,
    0.0019276015227660537,
    0.07028180360794067,
    0.4507637917995453,
    -0.49295592308044434,
    -1.4025129079818726,
    0.004871411714702845,
    -0.07546987384557724,
    0.21908120810985565,
    -0.11572597920894623,
    -0.26205974817276,
    1.49210524559021,
    -0.06724750250577927,
    -0.006715243216603994,
    0.49546146392822266,
    -0.16013123095035553,
    -0.0072193630039691925,
    0.17620287835597992,
    -0.01486311573535204,
    -0.029305564239621162,
    -0.0002956710522994399,
    -0.06280755251646042,
    0.12672635912895203,
    -0.005132699850946665,
    0.02269638329744339,
    0.16080448031425476,
    0.0025059175677597523,
    -0.17867450416088104,
    0.01440658699721098,
    0.03636698052287102,
    -0.5066424012184143,
    0.02877509780228138,
    0.00881605502218008,
    0.3213171064853668,
    -0.02290840819478035,
    -0.635996401309967,
    0.0043925149366259575,
    0.08247891813516617,
    0.026633551344275475,
    3.2133812055690214e-05,
    -0.3076537251472473,
    0.04133769869804382,
    -0.005951675120741129,
    0.04971091076731682,
    0.002068502129986882,
    0.6421986222267151,
    -0.0041797407902777195,
    -0.08229678869247437,
    -0.07289892435073853,
    1.5674303770065308,
    0.3048245906829834,
    -0.04505686089396477,
    0.3084387481212616,
    0.016024691984057426,
    0.06340692192316055,
    1.7178388833999634,
    0.12131684273481369,
    0.28837013244628906,
    -1.0541803021624219e-05,
    -0.21174423396587372,
    0.942180871963501,
    0.010137427598237991,
    -0.0757145807147026,
    0.04008299857378006,
    -0.10972311347723007,
    -0.31193098425865173,
    -0.12180301547050476,
    -0.29147833585739136,
    0.1462971270084381,
    0.23815301060676575,
    0.04600150138139725,
    -0.5218135714530945,
    0.06283582001924515,
    -0.7875805497169495,
    0.0965145155787468,
    -0.0002003239351324737,
    -0.13789866864681244,
    -7.033957081148401e-05,
    -0.28850314021110535,
    -0.5901474356651306,
    0.00496863154694438,
    0.328668475151062,
    -0.032743386924266815,
    0.05295995622873306,
    0.06409025192260742,
    0.003712432226166129,
    0.1894095242023468,
    -0.022204026579856873,
    0.2862190008163452,
    1.32943594455719,
    -0.16516849398612976,
    0.02095291204750538,
    -0.11087604612112045,
    -0.049383655190467834,
    0.006359392311424017,
    -0.10248616337776184,
    0.0006509962840937078,
    0.09422347694635391,
    0.355634868144989,
    -0.006292744539678097,
    0.024951457977294922,
    -0.018241500481963158,
    -0.017097437754273415,
    0.3145737051963806,
    0.06624379754066467,
    -0.16638396680355072,
    1.5053516626358032,
    0.24235020577907562,
    -0.5762912631034851,
    0.32950708270072937,
    0.09601391106843948,
    1.3889076709747314,
    0.0025756019167602062,
    -0.31690093874931335,
    -0.06086375191807747,
    -0.0002106574975186959,
    0.1327848583459854,
    0.08570785075426102,
    0.008493750356137753,
    0.39228585362434387,
    0.09630487859249115,
    0.0682884082198143,
    0.09001316130161285,
    -0.1680297553539276,
    1.3796025514602661,
    -0.5459851622581482,
    -0.26206138730049133,
    0.02434731088578701,
    0.41529375314712524,
    -0.4042781889438629,
    1.0842338800430298,
    0.004022670444101095,
    -0.03993091359734535,
    -0.009123754687607288,
    -1.3712128400802612,
    -0.14674340188503265,
    0.1594262570142746,
    0.010706565342843533,
    0.05239992216229439,
    -0.006569084711372852,
    -0.022755073383450508,
    -0.11891715228557587,
    -0.5278342366218567,
    -0.010683448053896427,
    0.010806205682456493,
    0.14795412123203278,
    -0.21136635541915894,
    -0.4660717844963074,
    0.006827210076153278,
    -0.1174037754535675,
    0.01812882348895073,
    0.025327609851956367,
    -0.0470399372279644,
    0.08898869901895523,
    6.664805550826713e-05,
    -0.7044727206230164,
    -0.04750655218958855,
    -0.022277142852544785,
    -0.003957696724683046,
    0.020614000037312508,
    -0.4027615189552307,
    -0.05019823834300041,
    -0.018058616667985916,
    0.04193933308124542,
    -0.4783862233161926,
    -0.005476829130202532,
    1.1347966194152832,
    0.020672747865319252,
    0.052768997848033905,
    -0.004293328151106834,
    -0.28375694155693054,
    0.2418287694454193,
    0.06797283887863159,
    -0.07049159705638885,
    0.4689405560493469,
    0.059445712715387344,
    0.286289244890213,
    0.013232841156423092,
    -0.1336686760187149,
    -0.41941359639167786,
    -0.35187286138534546,
    0.019520558416843414,
    -0.007891870103776455,
    0.014715686440467834,
    0.056993696838617325,
    -0.8518689870834351,
    0.0018533889669924974,
    0.16213035583496094,
    0.10734448581933975,
    0.33492013812065125,
    0.013962578028440475,
    0.4389928877353668,
    0.023989778012037277,
    0.08052133768796921,
    0.0006291382014751434,
    -0.6039122939109802,
    -0.0070955888368189335,
    0.09299279004335403,
    -0.12396909296512604,
    -0.01526168454438448,
    0.01758800633251667,
    0.08182477951049805,
    -0.0006640622159466147,
    0.0061808195896446705,
    -0.6090494990348816,
    -0.008829931728541851,
    -0.0929909497499466,
    0.00059044937370345,
    0.0430038757622242,
    0.11345631629228592,
    -0.11993331462144852,
    -0.017217542976140976,
    -0.12177617102861404,
    -0.10831738263368607,
    0.058568187057971954,
    0.035675786435604095,
    0.01913839392364025,
    -0.2139853686094284,
    -0.33559301495552063,
    0.003119338070973754,
    0.05244264379143715,
    0.002228717552497983,
    0.04519372433423996,
    0.019373640418052673,
    0.04378151521086693,
    -0.09702521562576294,
    -0.0017212595557793975,
    0.1615286022424698,
    -0.0051789795979857445,
    0.061034686863422394,
    -0.22312138974666595,
    0.16079658269882202,
    0.002256559208035469,
    0.037936918437480927,
    -0.038284365087747574,
    0.04160301387310028,
    1.0300737619400024,
    0.385345995426178,
    -0.00820050947368145,
    -0.21363425254821777,
    0.0049086506478488445,
    -0.2025609165430069,
    0.022366980090737343,
    -0.02951238863170147,
    -0.23667320609092712,
    -0.03248915448784828,
    0.021015487611293793,
    0.012852804735302925,
    -0.12352026253938675,
    0.0014156269608065486,
    0.026042427867650986,
    -0.45523035526275635,
    -0.05906808748841286,
    0.020272519439458847,
    -0.02846677042543888,
    -0.04029501974582672,
    0.23882272839546204,
    -0.06035729497671127,
    -0.07423018664121628,
    0.0022595999762415886,
    0.0014223171165212989,
    -0.10552988946437836,
    0.24942536652088165,
    0.015553591772913933,
    0.09611950814723969,
    -0.031018482521176338,
    0.7778903841972351,
    -0.013583231717348099,
    0.03502507880330086,
    -0.06124220788478851,
    -0.0041295685805380344,
    0.027557581663131714,
    0.02359098009765148,
    -0.005719457287341356,
    -0.030774470418691635,
    -0.02390400506556034,
    -0.011351069435477257,
    -0.014102289453148842,
    -0.054815515875816345,
    0.0939234271645546,
    0.05452963709831238,
    0.052318938076496124,
    0.018973499536514282,
    -0.08543278276920319,
    0.06517741084098816,
    -0.042601946741342545,
    0.010051335208117962,
    0.06118123233318329,
    0.021852241829037666,
    0.00019680474360939115,
    -0.02411273680627346,
    -0.0019568924326449633,
    0.06565451622009277,
    0.023410970345139503,
    0.010604728013277054,
    0.002598404884338379,
    -0.008788147941231728,
    0.06116854399442673,
    0.10865499079227448,
    0.24606938660144806,
    0.012759179808199406,
    0.011362815275788307,
    -0.049355294555425644,
    -0.03321551904082298,
    -0.03726503998041153,
    0.014032633975148201,
    -0.19107024371623993,
    0.034980855882167816,
    0.03040776215493679,
    -0.0007707972545176744,
    -0.003951214719563723,
    -0.08790045976638794,
    -0.001983585534617305,
    0.03636287525296211,
    0.014947147108614445,
    0.03285612910985947,
    -0.014762324281036854,
    0.019564999267458916,
    -0.006860614754259586,
    0.11309167742729187,
    -0.05583302676677704,
    -0.03399132937192917,
    -0.0010053605074062943,
    -0.1657889485359192,
    -0.09675193578004837,
    -0.11683041602373123,
    -0.031294479966163635,
    1.226698637008667,
    -0.05149806663393974,
    0.06247780844569206,
    -0.003052681917324662,
    -0.004240139853209257,
    0.08803672343492508,
    0.004076001700013876,
    -0.019225768744945526,
    0.009819666855037212,
    -0.04371335357427597,
    -0.13031361997127533,
    0.02047703228890896,
    -0.024865740910172462,
    -0.048258956521749496,
    0.005993333645164967,
    -0.04228837415575981,
    0.0009892894886434078,
    0.4769175052642822,
    0.13106104731559753,
    -0.08186497539281845,
    0.018980292603373528,
    -0.0028759827837347984,
    -0.0035641873255372047,
    0.05102159455418587,
    -0.013337119482457638,
    0.0035994963254779577,
    0.20294223725795746,
    -0.14011718332767487
  ],
  "opt_ratios": [
    9.536732250126079e-06,
    2.574548307165969e-05,
    6.190469866851345e-05,
    0.0001447592512704432,
    0.00032219282002188265,
    0.0006828769110143185,
    0.0013785986229777336,
    0.00265034893527627,
    0.004850450903177261,
    0.008444517850875854,
    0.01397106982767582,
    0.021936288103461266,
    0.032649263739585876,
    0.04606681317090988,
    0.06177840381860733,
    0.07922497391700745,
    0.09803581237792969,
    0.11818480491638184,
    0.13987722992897034,
    0.16339708864688873,
    0.18894869089126587,
    0.21648791432380676,
    0.24566739797592163,
    0.27592724561691284,
    0.306710422039032,
    0.3377038538455963,
    0.3689548671245575,
    0.4008314907550812,
    0.4339415729045868,
    0.4690416157245636,
    0.506939172744751,
    0.5483694672584534,
    0.593841552734375,
    0.6434308290481567,
    0.6966680884361267,
    0.7522546648979187,
    0.8077009916305542,
    0.8595584630966187,
    0.9044727683067322,
    0.9402540922164917,
    0.9664257764816284,
    0.984188973903656,
    0.9910905361175537,
    0.9041174650192261,
    0.955734372138977,
    0.9450347423553467,
    0.9016473293304443,
    0.9502459168434143,
    0.916914165019989,
    0.9395607709884644,
    0.9394184350967407
  ],
  "expectations": [
    -14.999982833862305,
    -15.709692001342773,
    -16.38382339477539,
    -17.015838623046875,
    -17.627857208251953,
    -18.21904754638672,
    -18.78749656677246,
    -19.33053970336914,
    -19.845317840576172,
    -20.32891845703125,
    -20.77840805053711,
    -21.190631866455078,
    -21.562448501586914,
    -21.890979766845703,
    -22.174762725830078,
    -22.41568374633789,
    -22.619579315185547,
    -22.795333862304688,
    -22.953067779541016,
    -23.102092742919922,
    -23.24910545349121,
    -23.397350311279297,
    -23.546619415283203,
    -23.69523811340332,
    -23.841230392456055,
    -23.983444213867188,
    -24.12198257446289,
    -24.25777244567871,
    -24.392187118530273,
    -24.526966094970703,
    -24.663917541503906,
    -24.804149627685547,
    -24.9482479095459,
    -25.09545135498047,
    -25.244125366210938,
    -25.391191482543945,
    -25.53144073486328,
    -25.65839195251465,
    -25.766525268554688,
    -25.85244369506836,
    -25.915855407714844,
    -25.959211349487305,
    -25.974668502807617,
    -25.70384979248047,
    -25.867645263671875,
    -25.833274841308594,
    -25.70254135131836,
    -25.849885940551758,
    -25.749799728393555,
    -25.817380905151367,
    -25.818653106689453
  ],
  "approx_ratios": [
    0.5769224166870117,
    0.6042189231285682,
    0.6301470536452073,
    0.6544553316556491,
    0.6779945080096905,
    0.7007325979379507,
    0.7225960217989408,
    0.7434822962834284,
    0.7632814554067758,
    0.7818814791165866,
    0.7991695404052734,
    0.8150243025559646,
    0.8293249423687274,
    0.8419607602632962,
    0.852875489455003,
    0.8621416825514573,
    0.8699838198148288,
    0.8767436100886419,
    0.8828102992131159,
    0.8885420285738431,
    0.8941963635958158,
    0.8998980888953576,
    0.9056392082801232,
    0.9113553120539739,
    0.9169703997098483,
    0.9224401620718149,
    0.927768560556265,
    0.9329912479107196,
    0.9381610430203952,
    0.9433448498065655,
    0.9486122131347656,
    0.9540057549109826,
    0.9595479965209961,
    0.9652096674992487,
    0.9709278987004206,
    0.9765842877901517,
    0.9819784898024339,
    0.9868612289428711,
    0.9910202026367188,
    0.9943247575026292,
    0.996763669527494,
    0.9984312057495117,
    0.9990257116464468,
    0.988609607403095,
    0.9949094332181491,
    0.9935874938964844,
    0.9885592827430139,
    0.9942263823289138,
    0.9903769126305213,
    0.992976188659668,
    0.9930251194880559
  ],
  "iter": 50,
  "best_iter": 42,
  "norm_history": [
    0.0019390827510505915,
    0.0019622191321104765,
    0.005019476171582937,
    0.0015758156077936292,
    0.0006295039784163237,
    0.00025084480876103044,
    0.00012900418369099498,
    7.101955998223275e-05,
    5.0046211981680244e-05,
    4.313259705668315e-05,
    2.221055365225766e-05,
    2.6063189579872414e-05,
    2.51999226748012e-05,
    1.737010825308971e-05,
    1.365504340355983e-05,
    1.3364705409912858e-05,
    1.1912263289559633e-05,
    8.311395504279062e-06,
    1.0259363989462145e-05,
    1.389907265547663e-05,
    8.166240149876103e-06,
    1.046530178427929e-05,
    1.7422293240088038e-05,
    7.42234669814934e-06,
    1.3749815479968674e-05,
    1.3511182260117494e-05,
    1.3477517313731369e-05,
    9.82615165412426e-06,
    1.6999183571897447e-05,
    1.7321510313195176e-05,
    2.7029867851524614e-05,
    3.473615652183071e-05,
    3.6148077924735844e-05,
    2.724595287872944e-05,
    4.260437344782986e-05,
    6.262003444135189e-05,
    8.87012283783406e-05,
    5.074243017588742e-05,
    7.766545604681596e-05,
    5.603661702480167e-05,
    0.00016892810526769608,
    0.00017329333059024066,
    0.0027800793759524822,
    0.0064419652335345745,
    0.004681956954300404,
    0.007150225806981325,
    0.005635719280689955,
    0.004371912684291601,
    0.011469556950032711,
    0.006056764628738165
  ],
  "w_history": [
    0,
    0.0,
    0.0025709445909271925,
    0.008257236807256384,
    0.014273546190272482,
    0.021019777545671043,
    0.02886679634051504,
    0.03820152215796035,
    0.04938776079130287,
    0.06277403391763721,
    0.07870907134646817,
    0.09759120817822224,
    0.11984240409964075,
    0.14588010028463022,
    0.17591810686430018,
    0.20959435094073697,
    0.2458199307019912,
    0.282909614890149,
    0.3189191666026612,
    0.35207988023276154,
    0.38122865659519833,
    0.4060329580279611,
    0.4270061226631262,
    0.4449940704577767,
    0.4608643434368515,
    0.4752013429469401,
    0.48819428168538426,
    0.4997722412675078,
    0.5097233712760313,
    0.5177245076011596,
    0.5234378685700144,
    0.5267538051443845,
    0.5277271766037731,
    0.5277271766037731,
    0.5277271766037731,
    0.5277271766037731,
    0.5277271766037731,
    0.5308841384967877,
    0.5396305844969983,
    0.5547914079309801,
    0.5760757508749941,
    0.602248114218959,
    0.6361078674120648,
    0.7812914499309443,
    0.7812914499309443,
    0.8174393040742578,
    0.891885120536632,
    0.891885120536632,
    0.9473870272196615,
    0.9473870272196615
  ],
  "edges": [
    [
      6,
      18
    ],
    [
      6,
      16
    ],
    [
      6,
      2
    ],
    [
      18,
      8
    ],
    [
      18,
      16
    ],
    [
      3,
      7
    ],
    [
      3,
      13
    ],
    [
      3,
      9
    ],
    [
      7,
      10
    ],
    [
      7,
      11
    ],
    [
      13,
      2
    ],
    [
      13,
      15
    ],
    [
      0,
      5
    ],
    [
      0,
      4
    ],
    [
      0,
      19
    ],
    [
      5,
      12
    ],
    [
      5,
      17
    ],
    [
      8,
      14
    ],
    [
      8,
      1
    ],
    [
      9,
      11
    ],
    [
      9,
      17
    ],
    [
      11,
      19
    ],
    [
      17,
      4
    ],
    [
      1,
      15
    ],
    [
      1,
      10
    ],
    [
      15,
      12
    ],
    [
      10,
      14
    ],
    [
      12,
      14
    ],
    [
      4,
      19
    ],
    [
      2,
      16
    ]
  ]
}