{
  "size": 18,
  "opt_val": -24.0,
  "method": "cQITE",
  "operations": [
    "Y0",
    "Y1",
    "Y2",
    "Y3",
    "Y4",
    "Y5",
    "Y6",
    "Y7",
    "Y8",
    "Y9",
    "Y10",
    "Y11",
    "Y12",
    "Y13",
    "Y14",
    "Y15",
    "Y16",
    "Y17",
    "Z0_Y15",
    "Z1_Y14",
    "Z2_Y13",
    "Z3_Y12",
    "Z4_Y11",
    "Z5_Y10",
    "Z6_Y9",
    "Z7_Y8",
    "Z16_Y17",
    "Y0_Z15",
    "Y1_Z14",
    "Y2_Z13",
    "Y3_Z12",
    "Y4_Z11",
    "Y5_Z10",
    "Y6_Z9",
    "Y7_Z8",
    "Y16_Z17",
    "Z16_Y14",
    "Z0_Y13",
    "Z1_Y12",
    "Z2_Y11",
    "Z3_Y10",
    "Z4_Y9",
    "Z5_Y8",
    "Z6_Y7",
    "Z15_Y17",
    "Y16_Z14",
    "Y0_Z13",
    "Y1_Z12",
    "Y2_Z11",
    "Y3_Z10",
    "Y4_Z9",
    "Y5_Z8",
    "Y6_Z7",
    "Y15_Z17",
    "Z15_Y13",
    "Z16_Y12",
    "Z0_Y11",
    "Z1_Y10",
    "Z2_Y9",
    "Z3_Y8",
    "Z4_Y7",
    "Z5_Y6",
    "Z14_Y17",
    "Y15_Z13",
    "Y16_Z12",
    "Y0_Z11",
    "Y1_Z10",
    "Y2_Z9",
    "Y3_Z8",
    "Y4_Z7",
    "Y5_Z6",
    "Y14_Z17",
    "Z14_Y12",
    "Z15_Y11",
    "Z16_Y10",
    "Z0_Y9",
    "Z1_Y8",
    "Z2_Y7",
    "Z3_Y6",
    "Z4_Y5",
    "Z13_Y17",
    "Y14_Z12",
    "Y15_Z11",
    "Y16_Z10",
    "Y0_Z9",
    "Y1_Z8",
    "Y2_Z7",
    "Y3_Z6",
    "Y4_Z5",
    "Y13_Z17",
    "Z13_Y11",
    "Z14_Y10",
    "Z15_Y9",
    "Z16_Y8",
    "Z0_Y7",
    "Z1_Y6",
    "Z2_Y5",
    "Z3_Y4",
    "Z12_Y17",
    "Y13_Z11",
    "Y14_Z10",
    "Y15_Z9",
    "Y16_Z8",
    "Y0_Z7",
    "Y1_Z6",
    "Y2_Z5",
    "Y3_Z4",
    "Y12_Z17",
    "Z12_Y10",
    "Z13_Y9",
    "Z14_Y8",
    "Z15_Y7",
    "Z16_Y6",
    "Z0_Y5",
    "Z1_Y4",
    "Z2_Y3",
    "Z11_Y17",
    "Y12_Z10",
    "Y13_Z9",
    "Y14_Z8",
    "Y15_Z7",
    "Y16_Z6",
    "Y0_Z5",
    "Y1_Z4",
    "Y2_Z3",
    "Y11_Z17",
    "Z11_Y9",
    "Z12_Y8",
    "Z13_Y7",
    "Z14_Y6",
    "Z15_Y5",
    "Z16_Y4",
    "Z0_Y3",
    "Z1_Y2",
    "Z10_Y17",
    "Y11_Z9",
    "Y12_Z8",
    "Y13_Z7",
    "Y14_Z6",
    "Y15_Z5",
    "Y16_Z4",
    "Y0_Z3",
    "Y1_Z2",
    "Y10_Z17",
    "Z10_Y8",
    "Z11_Y7",
    "Z12_Y6",
    "Z13_Y5",
    "Z14_Y4",
    "Z15_Y3",
    "Z16_Y2",
    "Z0_Y1",
    "Z9_Y17",
    "Y10_Z8",
    "Y11_Z7",
    "Y12_Z6",
    "Y13_Z5",
    "Y14_Z4",
    "Y15_Z3",
    "Y16_Z2",
    "Y0_Z1",
    "Y9_Z17",
    "Z9_Y7",
    "Z10_Y6",
    "Z11_Y5",
    "Z12_Y4",
    "Z13_Y3",
    "Z14_Y2",
    "Z15_Y1",
    "Z16_Y0",
    "Z8_Y17",
    "Y9_Z7",
    "Y10_Z6",
    "Y11_Z5",
    "Y12_Z4",
    "Y13_Z3",
    "Y14_Z2",
    "Y15_Z1",
    "Y16_Z0",
    "Y8_Z17",
    "Z8_Y6",
    "Z9_Y5",
    "Z10_Y4",
    "Z11_Y3",
    "Z12_Y2",
    "Z13_Y1",
    "Z14_Y0",
    "Z15_Y16",
    "Z7_Y17",
    "Y8_Z6",
    "Y9_Z5",
    "Y10_Z4",
    "Y11_Z3",
    "Y12_Z2",
    "Y13_Z1",
    "Y14_Z0",
    "Y15_Z16",
    "Y7_Z17",
    "Z7_Y5",
    "Z8_Y4",
    "Z9_Y3",
    "Z10_Y2",
    "Z11_Y1",
    "Z12_Y0",
    "Z13_Y16",
    "Z14_Y15",
    "Z6_Y17",
    "Y7_Z5",
    "Y8_Z4",
    "Y9_Z3",
    "Y10_Z2",
    "Y11_Z1",
    "Y12_Z0",
    "Y13_Z16",
    "Y14_Z15",
    "Y6_Z17",
    "Z6_Y4",
    "Z7_Y3",
    "Z8_Y2",
    "Z9_Y1",
    "Z10_Y0",
    "Z11_Y16",
    "Z12_Y15",
    "Z13_Y14",
    "Z5_Y17",
    "Y6_Z4",
    "Y7_Z3",
    "Y8_Z2",
    "Y9_Z1",
    "Y10_Z0",
    "Y11_Z16",
    "Y12_Z15",
    "Y13_Z14",
    "Y5_Z17",
    "Z5_Y3",
    "Z6_Y2",
    "Z7_Y1",
    "Z8_Y0",
    "Z9_Y16",
    "Z10_Y15",
    "Z11_Y14",
    "Z12_Y13",
    "Z4_Y17",
    "Y5_Z3",
    "Y6_Z2",
    "Y7_Z1",
    "Y8_Z0",
    "Y9_Z16",
    "Y10_Z15",
    "Y11_Z14",
    "Y12_Z13",
    "Y4_Z17",
    "Z4_Y2",
    "Z5_Y1",
    "Z6_Y0",
    "Z7_Y16",
    "Z8_Y15",
    "Z9_Y14",
    "Z10_Y13",
    "Z11_Y12",
    "Z3_Y17",
    "Y4_Z2",
    "Y5_Z1",
    "Y6_Z0",
    "Y7_Z16",
    "Y8_Z15",
    "Y9_Z14",
    "Y10_Z13",
    "Y11_Z12",
    "Y3_Z17",
    "Z3_Y1",
    "Z4_Y0",
    "Z5_Y16",
    "Z6_Y15",
    "Z7_Y14",
    "Z8_Y13",
    "Z9_Y12",
    "Z10_Y11",
    "Z2_Y17",
    "Y3_Z1",
    "Y4_Z0",
    "Y5_Z16",
    "Y6_Z15",
    "Y7_Z14",
    "Y8_Z13",
    "Y9_Z12",
    "Y10_Z11",
    "Y2_Z17",
    "Z2_Y0",
    "Z3_Y16",
    "Z4_Y15",
    "Z5_Y14",
    "Z6_Y13",
    "Z7_Y12",
    "Z8_Y11",
    "Z9_Y10",
    "Z1_Y17",
    "Y2_Z0",
    "Y3_Z16",
    "Y4_Z15",
    "Y5_Z14",
    "Y6_Z13",
    "Y7_Z12",
    "Y8_Z11",
    "Y9_Z10",
    "Y1_Z17",
    "Z1_Y16",
    "Z2_Y15",
    "Z3_Y14",
    "Z4_Y13",
    "Z5_Y12",
    "Z6_Y11",
    "Z7_Y10",
    "Z8_Y9",
    "Z0_Y17",
    "Y1_Z16",
    "Y2_Z15",
    "Y3_Z14",
    "Y4_Z13",
    "Y5_Z12",
    "Y6_Z11",
    "Y7_Z10",
    "Y8_Z9",
    "Y0_Z17"
  ],
  "dt": 0.05,
  "lr": 0.05,
  "lam": 1.0,
  "mu": 0.9,
  "fix_step": 0,
  "constant_c": true,
  "parameters": [
    -1.659202462178655e-05,
    -1.3294731616042554e-05,
    2.0925184799125418e-05,
    -3.0332031997204467e-07,
    -2.7888327167602256e-06,
    -6.286615098360926e-05,
    -1.6653854117976152e-06,
    -2.1787995137856342e-05,
    3.569883483578451e-05,
    -4.606621587299742e-06,
    -2.3438988137058914e-05,
    9.857292752712965e-06,
    8.770630665821955e-05,
    2.2361600713338703e-05,
    9.611254426999949e-06,
    -1.464510432924726e-06,
    -7.454553724528523e-06,
    3.600359195843339e-05,
    0.1595112830400467,
    0.5231755971908569,
    -0.15550421178340912,
    0.0782395750284195,
    -0.024781428277492523,
    0.09904681891202927,
    0.020573632791638374,
    -0.015082682482898235,
    -0.13661864399909973,
    -0.13883833587169647,
    0.13432621955871582,
    0.13206641376018524,
    0.04228514805436134,
    0.023374274373054504,
    -0.10231734067201614,
    0.004271003417670727,
    0.00576911773532629,
    0.10966946184635162,
    0.4221988022327423,
    0.17973484098911285,
    -0.07617262750864029,
    -0.5767378807067871,
    0.9860325455665588,
    0.148429274559021,
    0.4151058793067932,
    0.0536171980202198,
    0.16109168529510498,
    -0.07419385015964508,
    0.28292039036750793,
    -0.07804377377033234,
    -0.05825525149703026,
    -0.2356727123260498,
    -0.12342765182256699,
    0.1889268457889557,
    -0.3287419080734253,
    -0.1421314924955368,
    -0.1650194525718689,
    0.04377429559826851,
    -0.10752467066049576,
    0.13149432837963104,
    0.30905184149742126,
    -0.0034851126838475466,
    -0.12947243452072144,
    0.008845021016895771,
    0.020698746666312218,
    0.18620067834854126,
    -0.29101794958114624,
    -0.10898720473051071,
    -0.19002461433410645,
    -0.19674956798553467,
    -0.01587153971195221,
    0.1280360072851181,
    -0.01406277809292078,
    0.011720315553247929,
    -0.09447076171636581,
    -0.03711125627160072,
    -0.3710668087005615,
    0.10162551701068878,
    0.13179348409175873,
    0.5552610158920288,
    -0.23325659334659576,
    -0.103011354804039,
    0.2386016547679901,
    -0.2515196204185486,
    0.055508438497781754,
    0.8823551535606384,
    0.3617870807647705,
    0.6570607423782349,
    0.30105316638946533,
    -0.0049974643625319,
    -0.07167694717645645,
    -0.6570135951042175,
    0.07327604293823242,
    -0.008453414775431156,
    0.09966900199651718,
    0.06179701164364815,
    0.08723567426204681,
    0.04531800001859665,
    -0.12851202487945557,
    0.006575575098395348,
    0.24237821996212006,
    -0.058221086859703064,
    -0.19885407388210297,
    -0.05839499086141586,
    -0.01566118560731411,
    -0.5015828013420105,
    -0.0001281316945096478,
    0.28401318192481995,
    0.0436788871884346,
    -0.28596174716949463,
    0.012137236073613167,
    -0.06703121215105057,
    -0.02641138806939125,
    0.005721616558730602,
    0.09134455770254135,
    -0.36722421646118164,
    0.03239259868860245,
    0.6843294501304626,
    -0.19946569204330444,
    0.012442096136510372,
    -0.03833011910319328,
    -0.3317345976829529,
    -0.026476126164197922,
    -0.0737249031662941,
    0.022404253482818604,
    -0.11990023404359818,
    0.20779147744178772,
    0.2757500410079956,
    0.41782304644584656,
    0.06255132704973221,
    -0.0997268483042717,
    0.17794539034366608,
    0.045834824442863464,
    0.13788338005542755,
    -0.15226326882839203,
    -0.11331982165575027,
    -0.006153553258627653,
    0.019360153004527092,
    -0.1457219272851944,
    0.6540035605430603,
    -0.15830671787261963,
    -0.18207865953445435,
    0.21404118835926056,
    0.23598125576972961,
    0.11404401808977127,
    0.007949458435177803,
    0.029134126380085945,
    -0.0702657401561737,
    0.020792318508028984,
    0.050232674926519394,
    0.3468601703643799,
    -0.18780849874019623,
    0.010099801234900951,
    -0.07415835559368134,
    0.20717555284500122,
    0.018917804583907127,
    0.07734916359186172,
    -0.03972152993083,
    0.44878512620925903,
    0.10004891455173492,
    -0.1933804750442505,
    0.09858661144971848,
    0.085678830742836,
    -0.34819599986076355,
    -0.0005858344375155866,
    -0.2835289239883423,
    0.07710692286491394,
    0.8287181258201599,
    0.008024523966014385,
    -0.1011459082365036,
    0.18769295513629913,
    0.008730524219572544,
    -0.17830896377563477,
    0.1400057077407837,
    0.18911869823932648,
    0.14184342324733734,
    -0.17358167469501495,
    -0.07749807834625244,
    0.1756451278924942,
    0.35366958379745483,
    -0.0025756144896149635,
    0.07250616699457169,
    -0.0008200096781365573,
    -0.10620462149381638,
    -0.13871808350086212,
    0.31584566831588745,
    0.07529772073030472,
    0.021052807569503784,
    0.0347549170255661,
    -0.00222865235991776,
    0.27143099904060364,
    0.01948508806526661,
    -0.19022205471992493,
    -0.034453410655260086,
    0.2777738571166992,
    -0.07980075478553772,
    -0.07303803414106369,
    -0.01031248364597559,
    -0.06601888686418533,
    0.6793760657310486,
    -0.30291736125946045,
    0.11673057824373245,
    -0.004045048728585243,
    0.03683403134346008,
    0.036500874906778336,
    -0.07164597511291504,
    -0.03600974380970001,
    -0.09191127866506577,
    0.3711114823818207,
    -0.10364644974470139,
    0.012859396636486053,
    -0.14708559215068817,
    -0.1972539722919464,
    0.007892773486673832,
    0.10041043162345886,
    0.012534002773463726,
    -0.03493547439575195,
    0.041563861072063446,
    -0.07733602821826935,
    -0.10271547734737396,
    -0.01719428040087223,
    -0.11751682311296463,
    0.09429053962230682,
    0.09975039958953857,
    0.4110200107097626,
    -0.014277216978371143,
    0.03768691420555115,
    0.043826036155223846,
    -0.018943076953291893,
    -0.08367522805929184,
    -0.048328712582588196,
    -0.03127661347389221,
    0.00481565622612834,
    0.1113123744726181,
    -0.038397327065467834,
    0.20297452807426453,
    -0.04362668842077255,
    0.1292763203382492,
    0.01507589127868414,
    -0.20958548784255981,
    0.03588807210326195,
    0.17841197550296783,
    -0.027681145817041397,
    0.08515065908432007,
    0.04578927159309387,
    0.03228508681058884,
    1.0473383665084839,
    0.11585914343595505,
    0.15967461466789246,
    -0.03767749294638634,
    0.30213645100593567,
    -0.007030811160802841,
    -0.06752166897058487,
    -0.08784522861242294,
    0.0356731079518795,
    -0.00630543939769268,
    -0.05104600638151169,
    0.01927909441292286,
    -0.15133491158485413,
    0.028130363672971725,
    -0.028589341789484024,
    -0.038804054260253906,
    -0.03232128173112869,
    -0.1790316104888916,
    -0.008610725402832031,
    0.03507447987794876,
    0.02770860493183136,
    -0.079548180103302,
    -0.01656285859644413,
    -0.009916175156831741,
    -0.02945481799542904,
    0.0518815703690052,
    0.05205448716878891,
    -0.06492752581834793,
    0.03516470268368721,
    0.047886140644550323,
    -0.07229231297969818,
    0.13131889700889587,
    -0.007279300596565008,
    0.10045717656612396,
    -0.6043734550476074,
    0.008221062831580639,
    0.017006147652864456,
    -0.025173461064696312,
    -0.09741870313882828,
    0.08798923343420029,
    -0.1477353274822235,
    0.09710144251585007,
    -0.14512395858764648,
    -0.20226040482521057,
    0.07358895987272263,
    -0.18698839843273163,
    -0.013990904204547405,
    0.024967670440673828,
    -0.020937513560056686,
    -0.03380950167775154,
    -0.16022947430610657,
    -0.04189251363277435,
    -0.08574780076742172,
    0.06278907507658005,
    0.05313519388437271,
    -0.0007706135511398315,
    0.05751863867044449,
    0.02833971381187439,
    0.009252413176000118,
    -0.137067511677742,
    -0.04025274142622948,
    -0.012112976051867008,
    -0.28959110379219055,
    0.0694953054189682,
    0.06758559495210648,
    0.005809418391436338,
    0.5057587623596191,
    0.28504684567451477,
    -0.042413171380758286,
    0.490413099527359,
    0.38074585795402527,
    -0.08645088970661163,
    0.012834028340876102,
    0.01044732891023159,
    0.04567289352416992,
    0.17679868638515472,
    0.19286732375621796,
    0.0398857556283474,
    0.2506231367588043,
    0.6151379346847534
  ],
  "opt_ratios": [
    7.629386345797684e-06,
    1.9319042621646076e-05,
    4.4765831262338907e-05,
    9.663228411227465e-05,
    0.00019474938744679093,
    0.000367983418982476,
    0.0006547158118337393,
    0.0011014507617801428,
    0.0017592371441423893,
    0.0026779461186379194,
    0.0038985763676464558,
    0.005444786045700312,
    0.00731645617634058,
    0.00948982872068882,
    0.011928748339414597,
    0.014600751921534538,
    0.017486736178398132,
    0.02057766541838646,
    0.02386455237865448,
    0.02732720598578453,
    0.0309281088411808,
    0.03461252897977829,
    0.03831189125776291,
    0.04194451868534088,
    0.04541425406932831,
    0.04860891401767731,
    0.05140184238553047,
    0.05365486443042755,
    0.055222995579242706,
    0.05596229434013367,
    0.055750392377376556,
    0.054513752460479736,
    0.05225268006324768,
    0.049051109701395035,
    0.04506877809762955,
    0.04051649570465088,
    0.035622790455818176,
    0.030617592856287956,
    0.02573137730360031,
    0.021179893985390663,
    0.01712215691804886,
    0.013629723340272903,
    0.010698532685637474,
    0.008281750604510307,
    0.00631759874522686,
    0.004743593279272318,
    0.0035015761386603117,
    0.0025383075699210167,
    0.0018053048988804221,
    0.0012586936354637146,
    0.0008595738327130675
  ],
  "expectations": [
    -13.499984741210938,
    -14.146223068237305,
    -14.762682914733887,
    -15.353982925415039,
    -15.930249214172363,
    -16.487789154052734,
    -17.02179718017578,
    -17.526790618896484,
    -17.996673583984375,
    -18.425392150878906,
    -18.807720184326172,
    -19.139915466308594,
    -19.420394897460938,
    -19.649757385253906,
    -19.831140518188477,
    -19.96975326538086,
    -20.072586059570312,
    -20.1463680267334,
    -20.196775436401367,
    -20.227752685546875,
    -20.24175262451172,
    -20.240352630615234,
    -20.225217819213867,
    -20.197998046875,
    -20.160415649414062,
    -20.11361312866211,
    -20.057846069335938,
    -19.99216079711914,
    -19.914785385131836,
    -19.82331085205078,
    -19.715787887573242,
    -19.59124755859375,
    -19.450382232666016,
    -19.295669555664062,
    -19.131175994873047,
    -18.962160110473633,
    -18.793701171875,
    -18.630287170410156,
    -18.475296020507812,
    -18.330848693847656,
    -18.19792938232422,
    -18.07628631591797,
    -17.965106964111328,
    -17.863325119018555,
    -17.77008056640625,
    -17.684669494628906,
    -17.60659408569336,
    -17.535198211669922,
    -17.469974517822266,
    -17.410274505615234,
    -17.355453491210938
  ],
  "approx_ratios": [
    0.5624993642171224,
    0.5894259611765543,
    0.615111788113912,
    0.63974928855896,
    0.6637603839238485,
    0.6869912147521973,
    0.7092415491739908,
    0.7302829424540201,
    0.7498613993326823,
    0.7677246729532877,
    0.7836550076802572,
    0.797496477762858,
    0.8091831207275391,
    0.8187398910522461,
    0.8262975215911865,
    0.8320730527242025,
    0.8363577524820963,
    0.8394320011138916,
    0.841532309850057,
    0.8428230285644531,
    0.8434063593546549,
    0.8433480262756348,
    0.8427174091339111,
    0.841583251953125,
    0.8400173187255859,
    0.8380672136942545,
    0.8357435862223307,
    0.8330066998799642,
    0.8297827243804932,
    0.8259712855021158,
    0.8214911619822184,
    0.8163019816080729,
    0.8104325930277506,
    0.8039862314860026,
    0.7971323331197103,
    0.790090004603068,
    0.7830708821614584,
    0.7762619654337565,
    0.7698040008544922,
    0.7637853622436523,
    0.7582470575968424,
    0.753178596496582,
    0.7485461235046387,
    0.7443052132924398,
    0.7404200236002604,
    0.7368612289428711,
    0.73360808690389,
    0.7306332588195801,
    0.7279156049092611,
    0.7254281044006348,
    0.7231438954671224
  ],
  "iter": 50,
  "best_iter": 20,
  "norm_history": [
    0.0017671424429863691,
    0.001761345425620675,
    0.005026130937039852,
    0.001483635394833982,
    0.0005407686112448573,
    0.00021166313672438264,
    0.00013353166286833584,
    8.14024533610791e-05,
    4.756760972668417e-05,
    4.071885996381752e-05,
    2.939636578958016e-05,
    2.472461710567586e-05,
    2.0934452550136484e-05,
    1.3712206964555662e-05,
    1.0982043022522703e-05,
    1.1889878805959597e-05,
    8.440366400463972e-06,
    7.632198503415566e-06,
    8.373644959647208e-06,
    6.628813935094513e-06,
    6.344085250020726e-06,
    7.109887974365847e-06,
    8.784346391621511e-06,
    5.307294031808851e-06,
    5.813602456328226e-06,
    8.796684596745763e-06,
    4.166817234363407e-06,
    4.000849003205076e-06,
    4.078680376551347e-06,
    7.480372005375102e-06,
    5.529659574676771e-06,
    4.855057795793982e-06,
    5.987357326375786e-06,
    4.14789474234567e-06,
    5.765757123299409e-06,
    5.05231673741946e-06,
    4.654823896999005e-06,
    3.4620327369339066e-06,
    3.942910097975982e-06,
    4.180506948614493e-06,
    2.9533978249673964e-06,
    2.911496039814665e-06,
    2.6080149382323725e-06,
    2.8283084247959778e-06,
    2.7334476726537105e-06,
    2.530453230065177e-06,
    2.756568846962182e-06,
    2.2858318970975233e-06,
    2.46345553023275e-06,
    2.508268835299532e-06
  ],
  "w_history": [
    0
  ],
  "edges": [
    [
      7,
      17
    ],
    [
      7,
      13
    ],
    [
      7,
      2
    ],
    [
      17,
      0
    ],
    [
      17,
      6
    ],
    [
      4,
      12
    ],
    [
      4,
      14
    ],
    [
      4,
      16
    ],
    [
      12,
      15
    ],
    [
      12,
      5
    ],
    [
      3,
      10
    ],
    [
      3,
      11
    ],
    [
      3,
      2
    ],
    [
      10,
      15
    ],
    [
      10,
      16
    ],
    [
      14,
      16
    ],
    [
      14,
      1
    ],
    [
      5,
      13
    ],
    [
      5,
      8
    ],
    [
      13,
      0
    ],
    [
      8,
      9
    ],
    [
      8,
      1
    ],
    [
      9,
      11
    ],
    [
      9,
      0
    ],
    [
      11,
      6
    ],
    [
      15,
      1
    ],
    [
      6,
      2
    ]
  ]
}