{
  "size": 18,
  "opt_val": -23.0,
  "method": "AWQV",
  "operations": [
    "Y0",
    "Y1",
    "Y2",
    "Y3",
    "Y4",
    "Y5",
    "Y6",
    "Y7",
    "Y8",
    "Y9",
    "Y10",
    "Y11",
    "Y12",
    "Y13",
    "Y14",
    "Y15",
    "Y16",
    "Y17",
    "Z0_Y15",
    "Z1_Y14",
    "Z2_Y13",
    "Z3_Y12",
    "Z4_Y11",
    "Z5_Y10",
    "Z6_Y9",
    "Z7_Y8",
    "Z16_Y17",
    "Y0_Z15",
    "Y1_Z14",
    "Y2_Z13",
    "Y3_Z12",
    "Y4_Z11",
    "Y5_Z10",
    "Y6_Z9",
    "Y7_Z8",
    "Y16_Z17",
    "Z16_Y14",
    "Z0_Y13",
    "Z1_Y12",
    "Z2_Y11",
    "Z3_Y10",
    "Z4_Y9",
    "Z5_Y8",
    "Z6_Y7",
    "Z15_Y17",
    "Y16_Z14",
    "Y0_Z13",
    "Y1_Z12",
    "Y2_Z11",
    "Y3_Z10",
    "Y4_Z9",
    "Y5_Z8",
    "Y6_Z7",
    "Y15_Z17",
    "Z15_Y13",
    "Z16_Y12",
    "Z0_Y11",
    "Z1_Y10",
    "Z2_Y9",
    "Z3_Y8",
    "Z4_Y7",
    "Z5_Y6",
    "Z14_Y17",
    "Y15_Z13",
    "Y16_Z12",
    "Y0_Z11",
    "Y1_Z10",
    "Y2_Z9",
    "Y3_Z8",
    "Y4_Z7",
    "Y5_Z6",
    "Y14_Z17",
    "Z14_Y12",
    "Z15_Y11",
    "Z16_Y10",
    "Z0_Y9",
    "Z1_Y8",
    "Z2_Y7",
    "Z3_Y6",
    "Z4_Y5",
    "Z13_Y17",
    "Y14_Z12",
    "Y15_Z11",
    "Y16_Z10",
    "Y0_Z9",
    "Y1_Z8",
    "Y2_Z7",
    "Y3_Z6",
    "Y4_Z5",
    "Y13_Z17",
    "Z13_Y11",
    "Z14_Y10",
    "Z15_Y9",
    "Z16_Y8",
    "Z0_Y7",
    "Z1_Y6",
    "Z2_Y5",
    "Z3_Y4",
    "Z12_Y17",
    "Y13_Z11",
    "Y14_Z10",
    "Y15_Z9",
    "Y16_Z8",
    "Y0_Z7",
    "Y1_Z6",
    "Y2_Z5",
    "Y3_Z4",
    "Y12_Z17",
    "Z12_Y10",
    "Z13_Y9",
    "Z14_Y8",
    "Z15_Y7",
    "Z16_Y6",
    "Z0_Y5",
    "Z1_Y4",
    "Z2_Y3",
    "Z11_Y17",
    "Y12_Z10",
    "Y13_Z9",
    "Y14_Z8",
    "Y15_Z7",
    "Y16_Z6",
    "Y0_Z5",
    "Y1_Z4",
    "Y2_Z3",
    "Y11_Z17",
    "Z11_Y9",
    "Z12_Y8",
    "Z13_Y7",
    "Z14_Y6",
    "Z15_Y5",
    "Z16_Y4",
    "Z0_Y3",
    "Z1_Y2",
    "Z10_Y17",
    "Y11_Z9",
    "Y12_Z8",
    "Y13_Z7",
    "Y14_Z6",
    "Y15_Z5",
    "Y16_Z4",
    "Y0_Z3",
    "Y1_Z2",
    "Y10_Z17",
    "Z10_Y8",
    "Z11_Y7",
    "Z12_Y6",
    "Z13_Y5",
    "Z14_Y4",
    "Z15_Y3",
    "Z16_Y2",
    "Z0_Y1",
    "Z9_Y17",
    "Y10_Z8",
    "Y11_Z7",
    "Y12_Z6",
    "Y13_Z5",
    "Y14_Z4",
    "Y15_Z3",
    "Y16_Z2",
    "Y0_Z1",
    "Y9_Z17",
    "Z9_Y7",
    "Z10_Y6",
    "Z11_Y5",
    "Z12_Y4",
    "Z13_Y3",
    "Z14_Y2",
    "Z15_Y1",
    "Z16_Y0",
    "Z8_Y17",
    "Y9_Z7",
    "Y10_Z6",
    "Y11_Z5",
    "Y12_Z4",
    "Y13_Z3",
    "Y14_Z2",
    "Y15_Z1",
    "Y16_Z0",
    "Y8_Z17",
    "Z8_Y6",
    "Z9_Y5",
    "Z10_Y4",
    "Z11_Y3",
    "Z12_Y2",
    "Z13_Y1",
    "Z14_Y0",
    "Z15_Y16",
    "Z7_Y17",
    "Y8_Z6",
    "Y9_Z5",
    "Y10_Z4",
    "Y11_Z3",
    "Y12_Z2",
    "Y13_Z1",
    "Y14_Z0",
    "Y15_Z16",
    "Y7_Z17",
    "Z7_Y5",
    "Z8_Y4",
    "Z9_Y3",
    "Z10_Y2",
    "Z11_Y1",
    "Z12_Y0",
    "Z13_Y16",
    "Z14_Y15",
    "Z6_Y17",
    "Y7_Z5",
    "Y8_Z4",
    "Y9_Z3",
    "Y10_Z2",
    "Y11_Z1",
    "Y12_Z0",
    "Y13_Z16",
    "Y14_Z15",
    "Y6_Z17",
    "Z6_Y4",
    "Z7_Y3",
    "Z8_Y2",
    "Z9_Y1",
    "Z10_Y0",
    "Z11_Y16",
    "Z12_Y15",
    "Z13_Y14",
    "Z5_Y17",
    "Y6_Z4",
    "Y7_Z3",
    "Y8_Z2",
    "Y9_Z1",
    "Y10_Z0",
    "Y11_Z16",
    "Y12_Z15",
    "Y13_Z14",
    "Y5_Z17",
    "Z5_Y3",
    "Z6_Y2",
    "Z7_Y1",
    "Z8_Y0",
    "Z9_Y16",
    "Z10_Y15",
    "Z11_Y14",
    "Z12_Y13",
    "Z4_Y17",
    "Y5_Z3",
    "Y6_Z2",
    "Y7_Z1",
    "Y8_Z0",
    "Y9_Z16",
    "Y10_Z15",
    "Y11_Z14",
    "Y12_Z13",
    "Y4_Z17",
    "Z4_Y2",
    "Z5_Y1",
    "Z6_Y0",
    "Z7_Y16",
    "Z8_Y15",
    "Z9_Y14",
    "Z10_Y13",
    "Z11_Y12",
    "Z3_Y17",
    "Y4_Z2",
    "Y5_Z1",
    "Y6_Z0",
    "Y7_Z16",
    "Y8_Z15",
    "Y9_Z14",
    "Y10_Z13",
    "Y11_Z12",
    "Y3_Z17",
    "Z3_Y1",
    "Z4_Y0",
    "Z5_Y16",
    "Z6_Y15",
    "Z7_Y14",
    "Z8_Y13",
    "Z9_Y12",
    "Z10_Y11",
    "Z2_Y17",
    "Y3_Z1",
    "Y4_Z0",
    "Y5_Z16",
    "Y6_Z15",
    "Y7_Z14",
    "Y8_Z13",
    "Y9_Z12",
    "Y10_Z11",
    "Y2_Z17",
    "Z2_Y0",
    "Z3_Y16",
    "Z4_Y15",
    "Z5_Y14",
    "Z6_Y13",
    "Z7_Y12",
    "Z8_Y11",
    "Z9_Y10",
    "Z1_Y17",
    "Y2_Z0",
    "Y3_Z16",
    "Y4_Z15",
    "Y5_Z14",
    "Y6_Z13",
    "Y7_Z12",
    "Y8_Z11",
    "Y9_Z10",
    "Y1_Z17",
    "Z1_Y16",
    "Z2_Y15",
    "Z3_Y14",
    "Z4_Y13",
    "Z5_Y12",
    "Z6_Y11",
    "Z7_Y10",
    "Z8_Y9",
    "Z0_Y17",
    "Y1_Z16",
    "Y2_Z15",
    "Y3_Z14",
    "Y4_Z13",
    "Y5_Z12",
    "Y6_Z11",
    "Y7_Z10",
    "Y8_Z9",
    "Y0_Z17"
  ],
  "dt": 0.05,
  "lr": 0.05,
  "lam": 1.0,
  "mu": 0.9,
  "fix_step": 0,
  "constant_c": true,
  "parameters": [
    8.47222338506981e-07,
    -3.114627361355815e-06,
    1.5507407624681946e-06,
    4.027877366752364e-05,
    7.530190941906767e-06,
    -2.729863581407699e-06,
    3.452183605645587e-08,
    -9.598708857083693e-06,
    8.929929026635364e-05,
    3.936948814953212e-06,
    -8.133546543831471e-06,
    2.8916856535943225e-06,
    4.859080490859924e-06,
    2.5285844458267093e-06,
    4.3790882045868784e-05,
    -1.325244625149935e-06,
    4.756991984322667e-05,
    -8.347910807060543e-06,
    -0.0979958325624466,
    0.11783234030008316,
    0.0486048087477684,
    0.08000294864177704,
    -0.07637285441160202,
    0.03975382074713707,
    0.1563369184732437,
    0.07900978624820709,
    0.23216883838176727,
    0.09898187965154648,
    -0.11712861061096191,
    -0.03580419719219208,
    -0.07592230290174484,
    0.08433651924133301,
    -0.03816419094800949,
    -0.1642550230026245,
    0.2124931663274765,
    0.037353675812482834,
    0.014533154666423798,
    0.09205427020788193,
    0.22717051208019257,
    -0.7914212942123413,
    0.19308951497077942,
    0.43401452898979187,
    0.04519450664520264,
    -0.03030579537153244,
    -0.060303498059511185,
    -0.1437525749206543,
    -0.09692379832267761,
    -0.2293260246515274,
    0.8007451891899109,
    -0.22898007929325104,
    -0.4202839732170105,
    -0.01818515919148922,
    0.06326878815889359,
    0.07176074385643005,
    0.0940433219075203,
    0.1316310465335846,
    0.1994819939136505,
    0.35018783807754517,
    0.15187294781208038,
    -0.5436961650848389,
    -0.19895978271961212,
    0.07901135087013245,
    -0.029204994440078735,
    -0.08387615531682968,
    -0.09182101488113403,
    -0.2011238932609558,
    1.2032673358917236,
    -0.15216892957687378,
    0.6404192447662354,
    0.18133021891117096,
    -0.07441584020853043,
    0.050384681671857834,
    0.017522884532809258,
    -0.3382641673088074,
    -0.0017722677439451218,
    0.06979398429393768,
    0.33492618799209595,
    -0.27821820974349976,
    -0.09234379231929779,
    0.01860077679157257,
    -0.04707607999444008,
    0.027685701847076416,
    0.3409522473812103,
    0.891034722328186,
    -0.0683738961815834,
    0.0077468641102313995,
    0.29120880365371704,
    0.08620981872081757,
    -0.022622765973210335,
    0.0485445000231266,
    -0.13154882192611694,
    0.0022212923504412174,
    0.17328883707523346,
    -0.40408650040626526,
    0.3435050845146179,
    0.8488426208496094,
    0.34455740451812744,
    0.10877393186092377,
    -0.0758998841047287,
    0.12155187875032425,
    -0.03518715128302574,
    -0.17684440314769745,
    -0.15781009197235107,
    -0.3674999177455902,
    0.010232243686914444,
    -0.33859431743621826,
    -0.1423482894897461,
    0.10649053752422333,
    0.0015247056726366282,
    0.05701489746570587,
    -0.3947391211986542,
    -0.63800448179245,
    -0.0747419148683548,
    0.08203381299972534,
    -0.2871135175228119,
    0.011834901757538319,
    0.10043429583311081,
    -0.042563293129205704,
    -0.05243412032723427,
    -1.1585921049118042,
    0.6441903114318848,
    0.0959785059094429,
    -0.08683980256319046,
    -0.0013733564410358667,
    -0.04779903218150139,
    -0.11002746224403381,
    -0.017045747488737106,
    0.0859719067811966,
    0.16911661624908447,
    0.004125031176954508,
    -0.08463668078184128,
    -0.8934492468833923,
    -0.07504689693450928,
    0.8757745623588562,
    -0.21555142104625702,
    0.021455848589539528,
    1.4866265058517456,
    -0.1811314970254898,
    0.012051797471940517,
    0.08910265564918518,
    -0.19003646075725555,
    0.12899722158908844,
    -0.005167817231267691,
    -0.0005625108606182039,
    -0.017142577096819878,
    0.1963343769311905,
    -0.14143718779087067,
    0.7482269406318665,
    -0.09199501574039459,
    -0.11044416576623917,
    -0.016563192009925842,
    0.0006405265885405242,
    0.2870643436908722,
    -0.0013664949219673872,
    -0.21142816543579102,
    0.017528997734189034,
    -0.7453322410583496,
    -0.06275341659784317,
    0.025811972096562386,
    -0.021822595968842506,
    -0.2947065532207489,
    -0.3022412061691284,
    0.022897986695170403,
    -0.5978280305862427,
    -0.07460512220859528,
    0.19653348624706268,
    0.04692805930972099,
    0.005504110362380743,
    -0.0009589859982952476,
    -0.05717846751213074,
    0.12922826409339905,
    0.02491949126124382,
    0.006488087121397257,
    0.0731838196516037,
    -0.005384356249123812,
    -0.021229907870292664,
    -0.015272330492734909,
    0.14150838553905487,
    0.011873545125126839,
    0.00491478992626071,
    -0.08979927003383636,
    0.035172972828149796,
    -0.04429055005311966,
    -0.04712793603539467,
    -0.10368861258029938,
    0.00033175971475429833,
    -0.02308068238198757,
    -0.0014511668123304844,
    0.04111343249678612,
    -0.011865868233144283,
    -0.03302031755447388,
    0.025711001828312874,
    0.06921063363552094,
    0.021903064101934433,
    -0.04468606784939766,
    0.02843135967850685,
    -0.04207934811711311,
    -0.05658687651157379,
    0.9135106801986694,
    -0.14148388803005219,
    0.4061693549156189,
    -0.41874659061431885,
    0.003309182822704315,
    0.0010047528194263577,
    0.008908878080546856,
    -0.5543676614761353,
    0.06471375375986099,
    -0.8870412707328796,
    0.015227866359055042,
    -0.40858975052833557,
    0.01603347808122635,
    -0.6262820363044739,
    -0.003516839351505041,
    -0.006534329149872065,
    -0.05086011067032814,
    -0.028159089386463165,
    -0.013205332681536674,
    -0.21296916902065277,
    -0.05451890826225281,
    0.0007663958240300417,
    1.277435302734375,
    0.0003210256982129067,
    0.41541430354118347,
    0.010015929117798805,
    -0.06613284349441528,
    0.009844918735325336,
    0.28688040375709534,
    0.010953803546726704,
    0.050752200186252594,
    0.044989801943302155,
    -0.02413538098335266,
    0.015109429135918617,
    0.39300307631492615,
    0.06414657086133957,
    0.02163822390139103,
    -0.14726243913173676,
    -0.000775198161136359,
    -0.04557044431567192,
    -0.02693290449678898,
    -0.14538371562957764,
    -0.0012236845213919878,
    -0.3864128887653351,
    1.0906877517700195,
    -0.11557241529226303,
    0.22085478901863098,
    0.01299575250595808,
    -0.029822422191500664,
    1.4148125648498535,
    -0.006905296817421913,
    -0.01779278740286827,
    0.016196494922041893,
    0.33417508006095886,
    -0.0011983892181888223,
    -0.0006196433096192777,
    0.017747458070516586,
    -0.0010640420950949192,
    -0.4620373845100403,
    -0.026178235188126564,
    0.04510226100683212,
    -0.0018174337456002831,
    -0.007557668723165989,
    -0.05079174414277077,
    0.10472063720226288,
    0.21010302007198334,
    0.020840052515268326,
    0.03646481782197952,
    0.014967505820095539,
    0.002113517140969634,
    -0.0017600760329514742,
    -0.02925826609134674,
    0.003295481437817216,
    0.007385317236185074,
    0.0016869677929207683,
    0.10491541028022766,
    0.022419972345232964,
    0.7192627191543579,
    0.008950846269726753,
    0.1331617385149002,
    0.023399604484438896,
    -0.11140871793031693,
    0.08163679391145706,
    -0.058760866522789,
    -0.038688983768224716,
    1.2451626062393188,
    0.0037016503047198057,
    -0.07877157628536224,
    0.0038593437056988478,
    0.0007478793268091977,
    -0.029301144182682037,
    -0.0005447502480819821,
    0.01212193164974451,
    -0.006904246751219034,
    -0.06302406638860703,
    -0.04952968657016754,
    0.004150775261223316,
    0.04429081454873085,
    0.1991896629333496,
    0.14979435503482819,
    0.07762990891933441,
    0.14110057055950165,
    -0.931023120880127,
    0.09755536913871765,
    -0.24067752063274384,
    -0.008257045410573483,
    -0.008878744207322598,
    -0.0126514146104455,
    -0.005245786160230637,
    0.14824435114860535,
    0.00033137702848762274,
    0.06547006219625473,
    0.004761372227221727,
    0.7800060510635376,
    -0.00958066713064909,
    -0.12054938077926636,
    -0.005124008748680353,
    -0.018525902181863785,
    -0.0008175847469829023,
    1.407723069190979,
    -0.06090708449482918,
    0.46487635374069214,
    0.15991535782814026,
    0.03804205358028412,
    -0.013846629299223423,
    -0.05031301826238632
  ],
  "opt_ratios": [
    5.3405703511089087e-05,
    0.0001259590790141374,
    0.0002892392803914845,
    0.0005992568912915885,
    0.001162771019153297,
    0.002125596394762397,
    0.0036793521139770746,
    0.006056873127818108,
    0.009517545811831951,
    0.014321710914373398,
    0.02069639042019844,
    0.028797514736652374,
    0.03867967426776886,
    0.050288353115320206,
    0.06348899751901627,
    0.07814330607652664,
    0.09423530846834183,
    0.11198174953460693,
    0.13179495930671692,
    0.1541050374507904,
    0.1792502999305725,
    0.20747774839401245,
    0.23896914720535278,
    0.2738383114337921,
    0.31207767128944397,
    0.35343778133392334,
    0.39729219675064087,
    0.44264668226242065,
    0.48837363719940186,
    0.5334583520889282,
    0.5770653486251831,
    0.618475079536438,
    0.657087504863739,
    0.692563533782959,
    0.7249313592910767,
    0.7545297741889954,
    0.7817893028259277,
    0.8070335388183594,
    0.8304212093353271,
    0.8519786596298218,
    0.871675431728363,
    0.8894886374473572,
    0.9054461121559143,
    0.9196399450302124,
    0.9322236776351929,
    0.9433858394622803,
    0.9533089399337769,
    0.9621224403381348,
    0.9698853492736816,
    0.9766150712966919,
    0.9823368787765503
  ],
  "expectations": [
    -13.499984741210938,
    -14.127339363098145,
    -14.739505767822266,
    -15.306386947631836,
    -15.850176811218262,
    -16.368608474731445,
    -16.859403610229492,
    -17.320064544677734,
    -17.74852752685547,
    -18.142961502075195,
    -18.502368927001953,
    -18.826223373413086,
    -19.11453628540039,
    -19.36805534362793,
    -19.588531494140625,
    -19.77892303466797,
    -19.943941116333008,
    -20.090097427368164,
    -20.225011825561523,
    -20.355375289916992,
    -20.485889434814453,
    -20.61883544921875,
    -20.755142211914062,
    -20.895235061645508,
    -21.039043426513672,
    -21.185884475708008,
    -21.334224700927734,
    -21.481739044189453,
    -21.625947952270508,
    -21.764583587646484,
    -21.8961124420166,
    -22.01905632019043,
    -22.131893157958984,
    -22.233863830566406,
    -22.324934005737305,
    -22.405973434448242,
    -22.47844123840332,
    -22.54356575012207,
    -22.602264404296875,
    -22.655038833618164,
    -22.702329635620117,
    -22.74445343017578,
    -22.781810760498047,
    -22.81481170654297,
    -22.843952178955078,
    -22.869688034057617,
    -22.89249038696289,
    -22.912654876708984,
    -22.930347442626953,
    -22.94556999206543,
    -22.95842170715332
  ],
  "approx_ratios": [
    0.586955858313519,
    0.6142321462216584,
    0.6408480768618376,
    0.665495084679645,
    0.689138122226881,
    0.7116786293361498,
    0.7330175482708475,
    0.7530462845512058,
    0.7716751098632812,
    0.7888244131337041,
    0.8044508229131284,
    0.8185314510179602,
    0.8310667950174083,
    0.8420893627664318,
    0.8516752823539402,
    0.8599531754203464,
    0.8671278746231742,
    0.8734824968420941,
    0.8793483402418054,
    0.8850163169529127,
    0.8906908449919327,
    0.8964711064877717,
    0.9023974874745244,
    0.908488480941109,
    0.9147410185440726,
    0.9211254119873047,
    0.927574986996858,
    0.9339886540951936,
    0.9402586066204569,
    0.9462862429411515,
    0.9520048887833304,
    0.9573502747908883,
    0.9622562242590863,
    0.9666897317637568,
    0.9706493045972742,
    0.9741727580194888,
    0.9773235321044922,
    0.980155032614003,
    0.9827071480129076,
    0.985001688418181,
    0.9870578102443529,
    0.9888892795728601,
    0.9905135113260021,
    0.9919483350670856,
    0.9932153121284817,
    0.9943342623503312,
    0.9953256689983866,
    0.9962023859438689,
    0.9969716279403024,
    0.9976334779158883,
    0.9981922481371008
  ],
  "iter": 50,
  "best_iter": 50,
  "norm_history": [
    0.0017582876607775688,
    0.0017527113668620586,
    0.005041286814957857,
    0.0010587427532300353,
    0.0005787748377770185,
    0.00027443963335826993,
    0.00011649139923974872,
    7.684463344048709e-05,
    5.500444967765361e-05,
    3.0329558285302483e-05,
    2.2565305698662996e-05,
    1.6727888578316197e-05,
    1.5699481082265265e-05,
    1.3285855857247952e-05,
    1.15819320853916e-05,
    8.881861504050903e-06,
    6.22011293671676e-06,
    5.846442945767194e-06,
    6.482047865574714e-06,
    5.885653536097379e-06,
    7.555242973467102e-06,
    6.438755917770322e-06,
    6.260587724682409e-06,
    5.304119440552313e-06,
    7.606957296957262e-06,
    7.450282282661647e-06,
    1.0139138794329483e-05,
    7.038750936771976e-06,
    1.0299407222191803e-05,
    9.049078471434768e-06,
    6.2620410972158425e-06,
    1.1875510608660989e-05,
    8.85424560692627e-06,
    1.0304969691787846e-05,
    1.0725947504397482e-05,
    1.366329706797842e-05,
    2.1406034647952765e-05,
    1.5278686987585388e-05,
    1.9419145246502012e-05,
    2.697141098906286e-05,
    2.3198042981675826e-05,
    1.7615773685975e-05,
    3.137449311907403e-05,
    2.597824641270563e-05,
    2.5853356419247575e-05,
    3.801655475399457e-05,
    2.7684729502652772e-05,
    4.165250720689073e-05,
    3.562246638466604e-05,
    0.00011116451787529513
  ],
  "w_history": [
    0,
    0.0,
    0.0012253295294722298,
    0.006957454338581875,
    0.013709296610228773,
    0.02197592982383563,
    0.0321211875604936,
    0.04449652490388792,
    0.05936735403830945,
    0.0769730794346323,
    0.09742854593267761,
    0.12080173895724672,
    0.14710034889461043,
    0.1762262358906065,
    0.20790734219911963,
    0.24163323205741974,
    0.27649679927517773,
    0.31114431507214624,
    0.3439191120093554,
    0.3733964245214084,
    0.39869178766361435,
    0.41960467306739013,
    0.43631155665680943,
    0.4491100632174384,
    0.4584187957131628,
    0.4648137868183983,
    0.469101775994263,
    0.47229170024111716,
    0.47537181268121903,
    0.47918818770049876,
    0.48427311337415374,
    0.4911078257437252,
    0.5001664463387846,
    0.5116213063866448,
    0.5253724476207481,
    0.5409871947084205,
    0.5578318000373521,
    0.5754042307013443,
    0.593358420616037,
    0.6115409774327398,
    0.6298309007321093,
    0.6481655517331492,
    0.6664449103350457,
    0.6845662052338721,
    0.7023875678619078,
    0.7197886173383292,
    0.7366422538408217,
    0.752909355015266,
    0.7686130059262537,
    0.7838548423793941
  ],
  "edges": [
    [
      4,
      9
    ],
    [
      4,
      17
    ],
    [
      4,
      13
    ],
    [
      9,
      3
    ],
    [
      9,
      16
    ],
    [
      5,
      7
    ],
    [
      5,
      13
    ],
    [
      5,
      11
    ],
    [
      7,
      15
    ],
    [
      7,
      14
    ],
    [
      13,
      8
    ],
    [
      8,
      12
    ],
    [
      8,
      3
    ],
    [
      12,
      15
    ],
    [
      12,
      0
    ],
    [
      1,
      6
    ],
    [
      1,
      2
    ],
    [
      1,
      10
    ],
    [
      6,
      11
    ],
    [
      6,
      2
    ],
    [
      2,
      11
    ],
    [
      3,
      14
    ],
    [
      15,
      0
    ],
    [
      17,
      14
    ],
    [
      17,
      16
    ],
    [
      16,
      10
    ],
    [
      0,
      10
    ]
  ]
}